lesscode/__init__.py
lesscode/version.py
lesscode/db/__init__.py
lesscode/db/base_connection_pool.py
lesscode/db/base_sql_helper.py
lesscode/db/condition_wrapper.py
lesscode/db/connection_info.py
lesscode/db/db_function.py
lesscode/db/ds_helper.py
lesscode/db/init_connection_pool.py
lesscode/db/page.py
lesscode/db/relational_db_helper.py
lesscode/db/clickhouse/__init__.py
lesscode/db/clickhouse/clickhouse_helper.py
lesscode/db/clickhouse/clickhouse_pool.py
lesscode/db/dm/__init__.py
lesscode/db/dm/dm_helper.py
lesscode/db/dm/dm_pool.py
lesscode/db/elasticsearch/__init__.py
lesscode/db/elasticsearch/elasticsearch_helper.py
lesscode/db/elasticsearch/elasticsearch_pool.py
lesscode/db/es/__init__.py
lesscode/db/es/es_helper.py
lesscode/db/es/es_pool.py
lesscode/db/es/es_request.py
lesscode/db/generic/__init__.py
lesscode/db/generic/generic_helper.py
lesscode/db/generic/generic_pool.py
lesscode/db/mongodb/__init__.py
lesscode/db/mongodb/base_model.py
lesscode/db/mongodb/mongodb_helper.py
lesscode/db/mongodb/mongodb_pool.py
lesscode/db/mysql/__init__.py
lesscode/db/mysql/mysql_helper.py
lesscode/db/mysql/mysql_pool.py
lesscode/db/nebula/__init__.py
lesscode/db/nebula/nebula_helper.py
lesscode/db/nebula/nebula_pool.py
lesscode/db/neo4j/__init__.py
lesscode/db/neo4j/neo4j_helper.py
lesscode/db/neo4j/neo4j_pool.py
lesscode/db/postgresql/__init__.py
lesscode/db/postgresql/postgresql_helper.py
lesscode/db/postgresql/postgresql_pool.py
lesscode/db/redis/__init__.py
lesscode/db/redis/redis_helper.py
lesscode/db/redis/redis_pool.py
lesscode/db/redis_cluster/__init__.py
lesscode/db/redis_cluster/redis_cluster_helper.py
lesscode/db/redis_cluster/redis_cluster_pool.py
lesscode/db/sqlalchemy/__init__.py
lesscode/db/sqlalchemy/sqlalchemy_helper.py
lesscode/db/sqlalchemy/sqlalchemy_model_service.py
lesscode/db/sqlalchemy/sqlalchemy_pool.py
lesscode/extend_handlers/__init__.py
lesscode/extend_handlers/not_found_handler.py
lesscode/extend_handlers/doc/__init__.py
lesscode_py-0.4.21.dist-info/METADATA
lesscode_py-0.4.21.dist-info/WHEEL
lesscode_py-0.4.21.dist-info/top_level.txt
lesscode_py-0.4.21.dist-info/RECORD
