Metadata-Version: 2.1
Name: lesscode-py
Version: 0.4.21
Summary: lesscode-python 是基于tornado的web开发脚手架项目，该项目初衷为简化开发过程，让研发人员更加关注业务。
Home-page: https://gitee.com/yongchao9/lesscode-python
Author: Chao.yy
Author-email: yuyc@ishangqi.com
Platform: python
Classifier: Programming Language :: Python :: 3
Classifier: Operating System :: OS Independent
Requires-Python: >=3.6
